client/__init__.py
client/client.py
client/client/__init__.py
client/client/client_gui.py
client/client/db_client.py
client/client/main_window_conv.py
client/client/transport.py
client/common/__init__.py
client/common/decorators.py
client/common/descriptors.py
client/common/errors.py
client/common/metaclasses.py
client/common/utils.py
client/common/variables.py
client/doc/__init__.py
client/doc/source/__init__.py
client/doc/source/conf.py
client/log/__init__.py
client/log/client_log_config.py
client/unittests/__init__.py
client/unittests/test_utils.py
py_messenger_client-0.1.2.data/scripts/client_run
py_messenger_client-0.1.2.dist-info/METADATA
py_messenger_client-0.1.2.dist-info/WHEEL
py_messenger_client-0.1.2.dist-info/top_level.txt
py_messenger_client-0.1.2.dist-info/RECORD
